rrstats.py
rrstats-0.1.dist-info/METADATA
rrstats-0.1.dist-info/WHEEL
rrstats-0.1.dist-info/licenses/LICENSE
rrstats-0.1.dist-info/RECORD
