Metadata-Version: 2.4
Name: rrstats
Version: 0.1
Summary: My statistics base utils for my other projects
Author-email: RadoTheProgrammer <rrrado15@gmail.com>
License-Expression: MIT
License-File: LICENSE
Classifier: Operating System :: OS Independent
Classifier: Programming Language :: Python :: 3
Requires-Python: >=3.13
Requires-Dist: matplotlib>=3.10.3
Requires-Dist: numpy>=2.2.5
Requires-Dist: pandas>=2.2.3
